pydrishti/__init__.py
pydrishti/extract.py
pydrishti/main.py
pydrishti/process.py
pydrishti/utils.py
pydrishti-0.1.dist-info/METADATA
pydrishti-0.1.dist-info/WHEEL
pydrishti-0.1.dist-info/top_level.txt
pydrishti-0.1.dist-info/RECORD
