Metadata-Version: 2.1
Name: pydrishti
Version: 0.1
Summary: Image processing simplified
Home-page: https://github.com/TheMrinalSinha/drishti
Author: Mrinal Sinha
Author-email: mail@themrinalsinha.com
License: UNKNOWN
Platform: UNKNOWN
Classifier: Programming Language :: Python :: 3
Requires-Dist: dlib
Requires-Dist: pyocr
Requires-Dist: numpy
Requires-Dist: Pillow
Requires-Dist: imutils
Requires-Dist: ipython
Requires-Dist: matplotlib
Requires-Dist: opencv-contrib-python
